[
    {
        "id": "openPopup1",
        "image": "親子丼.jpg",
        "description": "親子丼です。",  
        "allergies": "", 
        "alt": "親子丼サンプル",
        "price": 450
    },
    {
        "id": "openPopup2",
        "image": "塩豚丼.jpg",
        "description": "塩豚丼です。",  
        "allergies": "", 
        "alt": "塩豚丼サンプル",
        "price": 450
    },
    {
        "id": "openPopup3",
        "image": "ソースカツ丼.jpg",
        "description": "ソースカツ丼です。",  
        "allergies": "", 
        "alt": "ソースカツ丼サンプル",
        "price": 450
    },
    {
        "id": "openPopup4",
        "image": "カツ丼.jpg",
        "description": "カツ丼です。",  
        "allergies": "", 
        "alt": "カツ丼サンプル",
        "price": 480
    },
    {
        "id": "openPopup5",
        "image": "デミカツ丼.jpg",
        "description": "デミカツ丼です。",  
        "allergies": "", 
        "alt": "デミカツ丼サンプル",
        "price": 480
    },
    {
        "id": "openPopup6",
        "image": "チキン南蛮丼.jpg",
        "description": "チキン南蛮丼です。",  
        "allergies": "", 
        "alt": "チキン南蛮丼サンプル",
        "price": 480
    },
    {
        "id": "openPopup7",
        "image": "唐揚げマヨ丼.jpg",
        "description": "唐揚げマヨ丼です。",  
        "allergies": "", 
        "alt": "唐揚げマヨ丼サンプル",
        "price": 480
    },
    {
        "id": "openPopup8",
        "image": "韓国風ユッケ丼.jpg",
        "description": "韓国風ユッケ丼です。",  
        "allergies": "", 
        "alt": "韓国風ユッケ丼サンプル",
        "price": 480
    },
    {
        "id": "openPopup9",
        "image": "スペシャルフライチキン丼.jpg",
        "description": "スペシャルフライチキン丼です。",  
        "allergies": "", 
        "alt": "スペシャルフライチキン丼サンプル",
        "price": 500
    },
    {
        "id": "openPopup10",
        "image": "醤油ラーメン.jpg",
        "description": "醤油ラーメンです。",  
        "allergies": "", 
        "alt": "醤油ラーメンサンプル",
        "price": 380
    },
    {
        "id": "openPopup11",
        "image": "豚骨ラーメン.jpg",
        "description": "豚骨ラーメンです。",  
        "allergies": "", 
        "alt": "豚骨ラーメンサンプル",
        "price": 380
    },
    {
        "id": "openPopup12",
        "image": "キムチ豚骨ラーメン.jpg",
        "description": "キムチ豚骨ラーメンです。",  
        "allergies": "", 
        "alt": "キムチ豚骨ラーメンサンプル",
        "price": 430
    },
    {
        "id": "openPopup13",
        "image": "かけうどん.jpg",
        "description": "かけうどんです。",  
        "allergies": "", 
        "alt": "かけうどんサンプル",
        "price": 350
    },
    {
        "id": "openPopup14",
        "image": "きつねうどん.jpg",
        "description": "きつねうどんです。",  
        "allergies": "", 
        "alt": "きつねうどんサンプル",
        "price": 400
    },
    {
        "id": "openPopup15",
        "image": "月見うどん.jpg",
        "description": "月見うどんです。",  
        "allergies": "", 
        "alt": "月見うどんサンプル",
        "price": 400
    },
    {
        "id": "openPopup16",
        "image": "とろろ昆布うどん.jpg",
        "description": "とろろ昆布うどんです。",  
        "allergies": "", 
        "alt": "とろろ昆布うどんサンプル",
        "price": 400
    },
    {
        "id": "openPopup17",
        "image": "カレーうどん.jpg",
        "description": "カレーうどんです。",  
        "allergies": "", 
        "alt": "カレーうどんサンプル",
        "price": 450
    },
    {
        "id": "openPopup18",
        "image": "カレーライス.jpg",
        "description": "カレーライスです。",  
        "allergies": "", 
        "alt": "カレーライスサンプル",
        "price": 400
    },
    {
        "id": "openPopup19",
        "image": "カツカレー.jpg",
        "description": "カツカレーです。",  
        "allergies": "", 
        "alt": "カツカレーサンプル",
        "price": 500
    },
    {
        "id": "openPopup20",
        "image": "ポテトフライ.jpg",
        "description": "ポテトフライです。",  
        "allergies": "", 
        "alt": "ポテトフライサンプル",
        "price": 160
    },
    {
        "id": "openPopup21",
        "image": "唐揚げさん.jpg",
        "description": "唐揚げさんです。",  
        "allergies": "", 
        "alt": "唐揚げさんサンプル",
        "price": 200
    },
    {
        "id": "openPopup22",
        "image": "食堂のコロッケ.jpg",
        "description": "食堂のコロッケです。",  
        "allergies": "", 
        "alt": "食堂のコロッケサンプル",
        "price": 70
    },
    {
        "id": "openPopup23",
        "image": "チュロス.jpg",
        "description": "チュロスです。",  
        "allergies": "", 
        "alt": "チュロスサンプル",
        "price": 160
    },
    {
        "id": "openPopup24",
        "image": "ワッフル.jpg",
        "description": "ワッフルです。",  
        "allergies": "", 
        "alt": "ワッフルサンプル",
        "price": 160
    },
    {
        "id": "openPopup25",
        "image": "菓子パン各種.jpg",
        "description": "菓子パン各種です。",  
        "allergies": "", 
        "alt": "菓子パン各種サンプル",
        "price": 170
    },
    {
        "id": "openPopup26",
        "image": "アイス各種.jpg",
        "description": "アイス各種です。",  
        "allergies": "", 
        "alt": "アイス各種サンプル",
        "price": 180
    },
    {
        "id": "openPopup27",
        "image": "おにぎり.jpg",
        "description": "おにぎりです。",  
        "allergies": "", 
        "alt": "おにぎりサンプル",
        "price": 120
    }
]